configdict/__init__.py
configdict/configdict.py
configdict/py.typed
configdict/__pycache__/configdict.cpython-38.pyc
configdict-2.13.4.dist-info/licenses/LICENSE.md
configdict-2.13.4.dist-info/METADATA
configdict-2.13.4.dist-info/WHEEL
configdict-2.13.4.dist-info/top_level.txt
configdict-2.13.4.dist-info/RECORD
