Metadata-Version: 2.4
Name: configdict
Version: 2.13.4
Summary: A supercharged dict used as configuration
Author-email: Eduardo Moguillansky <eduardo.moguillansky@gmail.com>
License: Copyright (c) 2011-2017 GitHub Inc.
Project-URL: Homepage, https://github.com/gesellkammer/configdict
Classifier: Programming Language :: Python :: 3
Classifier: Operating System :: OS Independent
Requires-Python: >=3.9
License-File: LICENSE.md
Requires-Dist: setuptools
Requires-Dist: appdirs
Requires-Dist: PyYAML
Requires-Dist: watchdog
Requires-Dist: thefuzz
Dynamic: license-file
